README.md
myrsa.py
setup.py
myrsa.egg-info/PKG-INFO
myrsa.egg-info/SOURCES.txt
myrsa.egg-info/dependency_links.txt
myrsa.egg-info/requires.txt
myrsa.egg-info/top_level.txt